instacrawl/.DS_Store
instacrawl/__init__.py
instacrawl/analysis.py
instacrawl/cli_utils.py
instacrawl/console.py
instacrawl/insta.py
instacrawl/main.py
instacrawl/prompts.py
instacrawl/steps.py
instacrawl/verbose.py
instacrawl-0.1.5.dist-info/METADATA
instacrawl-0.1.5.dist-info/WHEEL
instacrawl-0.1.5.dist-info/entry_points.txt
instacrawl-0.1.5.dist-info/RECORD
